{
  "risk_label": "Medium",
  "score": 55,
  "matched_rules": [
    "Suspicion Determined After Booking",
    "Potential Sanctions Hit"
  ],
  "explanation": "The transaction triggers a violation of Clause 6.2 \u2013 the bank proceeded with the transaction after suspicion was determined and a potential sanctions hit was identified. No other major AML/CFT rule breaches are evident, so the overall risk is assessed as Medium.",
  "transaction_id": "9db0c15a-8d81-4f97-80aa-32edecc7068d",
  "index": 14
}